README.md
setup.py
picol/__init__.py
picol/picol.py
picol.egg-info/PKG-INFO
picol.egg-info/SOURCES.txt
picol.egg-info/dependency_links.txt
picol.egg-info/entry_points.txt
picol.egg-info/requires.txt
picol.egg-info/top_level.txt
picol/fonts/OpenSans-Bold.ttf
picol/fonts/OpenSans-ExtraBold.ttf
picol/fonts/OpenSans-ExtraBoldItalic.ttf
picol/fonts/OpenSans-Italic.ttf
picol/fonts/OpenSans-Light.ttf
picol/fonts/OpenSans-LightItalic.ttf
picol/fonts/OpenSans-Regular.ttf
picol/fonts/OpenSans-Semibold.ttf
picol/fonts/OpenSans-SemiboldItalic.ttf