Metadata-Version: 2.1
Name: picol
Version: 0.2
Summary: picol (pronounced "pickle") will fetch the ten most used colors in an image and present the hex colors.
Home-page: UNKNOWN
Author: armandg
Author-email: armandg@gmail.com
License: GPL-v3.0
Platform: UNKNOWN
